{
  "metadata_success": true,
  "user_input": "Vivy Fluorite Eyes Song",
  "selected_title": "Vivy -Fluorite Eye’s Song-",
  "anime_id": 40266,
  "confidence": 95,
  "metadata": {
    "name": "Vivy -Fluorite Eye’s Song-",
    "air_year_quarter": "2021년 2분기",
    "avg_rating": 4.7,
    "status": "완결",
    "laftel_url": "https://laftel.net/item/40266",
    "cover_url": "https://thumbnail.laftel.net/items/thumbs/big/a6c6ec4a-c4c2-45d9-b255-bb88e30d6113.jpg",
    "production": "WIT STUDIO",
    "total_episodes": 14
  },
  "timestamp": "2025-08-22T17:11:49.522225"
}