{
  "metadata_success": true,
  "user_input": "명탐정 코난 극장판 2기: 14번째의 표적",
  "selected_title": "(더빙) 극장판 명탐정 코난 2기: 열네번째 표적",
  "anime_id": 16920,
  "confidence": 95,
  "metadata": {
    "name": "(더빙) 극장판 명탐정 코난 2기: 열네번째 표적",
    "air_year_quarter": "1998년 2분기",
    "avg_rating": 4.2,
    "status": "완결",
    "laftel_url": "https://laftel.net/item/16920",
    "cover_url": "https://thumbnail.laftel.net/items/thumbs/big/f49c0f9d-f561-43f8-84c7-f253aeff9e94.jpg",
    "production": "TMS 엔터테인먼트",
    "total_episodes": 1
  },
  "timestamp": "2025-08-22T17:12:38.250380"
}