{
  "upload_success": true,
  "notion_page_id": "b449c677-3702-47dd-ab15-266264c02788",
  "notion_page_url": "https://www.notion.so/Vivy-Fluorite-Eyes-Song-b449c677370247ddab15266264c02788",
  "uploaded_fields": {
    "이름": {
      "title": [
        {
          "text": {
            "content": "Vivy Fluorite Eyes Song"
          }
        }
      ]
    },
    "라프텔 제목": {
      "rich_text": [
        {
          "text": {
            "content": "Vivy -Fluorite Eye’s Song-"
          }
        }
      ]
    },
    "방영 분기": {
      "multi_select": [
        {
          "name": "2021년 2분기"
        }
      ]
    },
    "라프텔 평점": {
      "number": 4.7
    },
    "방영 상태": {
      "select": {
        "name": "완결"
      }
    },
    "라프텔 URL": {
      "url": "https://laftel.net/item/40266"
    },
    "표지": {
      "files": [
        {
          "type": "external",
          "name": "Cover Image",
          "external": {
            "url": "https://thumbnail.laftel.net/items/thumbs/big/a6c6ec4a-c4c2-45d9-b255-bb88e30d6113.jpg"
          }
        }
      ]
    },
    "제작사": {
      "select": {
        "name": "WIT STUDIO"
      }
    },
    "총 화수": {
      "number": 14
    }
  },
  "action": "업데이트",
  "upload_timestamp": "2025-08-22T17:11:50.497954",
  "user_input": "Vivy Fluorite Eyes Song"
}